vflow/__init__.py
vflow/helpers.py
vflow/pipeline.py
vflow/subkey.py
vflow/utils.py
vflow/vfunc.py
vflow/vset.py
vflow-0.1.4.dist-info/METADATA
vflow-0.1.4.dist-info/WHEEL
vflow-0.1.4.dist-info/RECORD
