Metadata-Version: 2.1
Name: vflow
Version: 0.1.4
Summary: A framework for doing stability analysis with PCS.
Project-URL: Homepage, https://vflow.csinva.io/
Project-URL: Issues, https://github.com/Yu-Group/veridical-flow/issues
Author-email: Chandan Singh <chandan_singh@berkeley.edu>, James Duncan <jpduncan@berkeley.edu>, Abhineet Agarwal <aa3797@berkeley.edu>, Rush Kapoor <rush.kapoor@berkeley.edu>
Maintainer-email: James Duncan <jpduncan@berkeley.edu>
License: MIT
Classifier: Development Status :: 3 - Alpha
Classifier: Intended Audience :: Science/Research
Classifier: License :: OSI Approved :: MIT License
Classifier: Operating System :: OS Independent
Classifier: Programming Language :: Python :: 3
Classifier: Topic :: Scientific/Engineering :: Artificial Intelligence
Requires-Python: >=3.9
Requires-Dist: joblib
Requires-Dist: matplotlib
Requires-Dist: mlflow
Requires-Dist: networkx
Requires-Dist: numpy
Requires-Dist: pandas>=2.0.0
Requires-Dist: pytest
Requires-Dist: ray
Requires-Dist: scipy
Provides-Extra: nb
Requires-Dist: jupyter; extra == 'nb'
Requires-Dist: jupyterlab; extra == 'nb'
Requires-Dist: scikit-learn>=0.23.0; extra == 'nb'
Requires-Dist: torch>=1.0.0; extra == 'nb'
Requires-Dist: torchvision; extra == 'nb'
Requires-Dist: tqdm; extra == 'nb'
